{
  "openapi": "3.0.1",
  "info": {
    "title": "api_app_pizza_flutter",
    "version": "1.0"
  },
  "paths": {
    "/api/Address": {
      "get": {
        "tags": [
          "Address"
        ],
        "responses": {
          "200": {
            "description": "OK",
            "content": {
              "text/plain": {
                "schema": {
                  "type": "array",
                  "items": {
                    "$ref": "#/components/schemas/Address"
                  }
                }
              },
              "application/json": {
                "schema": {
                  "type": "array",
                  "items": {
                    "$ref": "#/components/schemas/Address"
                  }
                }
              },
              "text/json": {
                "schema": {
                  "type": "array",
                  "items": {
                    "$ref": "#/components/schemas/Address"
                  }
                }
              }
            }
          }
        }
      },
      "post": {
        "tags": [
          "Address"
        ],
        "requestBody": {
          "content": {
            "application/json": {
              "schema": {
                "$ref": "#/components/schemas/Address"
              }
            },
            "text/json": {
              "schema": {
                "$ref": "#/components/schemas/Address"
              }
            },
            "application/*+json": {
              "schema": {
                "$ref": "#/components/schemas/Address"
              }
            }
          }
        },
        "responses": {
          "200": {
            "description": "OK",
            "content": {
              "text/plain": {
                "schema": {
                  "$ref": "#/components/schemas/Address"
                }
              },
              "application/json": {
                "schema": {
                  "$ref": "#/components/schemas/Address"
                }
              },
              "text/json": {
                "schema": {
                  "$ref": "#/components/schemas/Address"
                }
              }
            }
          }
        }
      }
    },
    "/api/Address/{id}": {
      "get": {
        "tags": [
          "Address"
        ],
        "parameters": [
          {
            "name": "id",
            "in": "path",
            "required": true,
            "schema": {
              "type": "integer",
              "format": "int32"
            }
          }
        ],
        "responses": {
          "200": {
            "description": "OK",
            "content": {
              "text/plain": {
                "schema": {
                  "$ref": "#/components/schemas/Address"
                }
              },
              "application/json": {
                "schema": {
                  "$ref": "#/components/schemas/Address"
                }
              },
              "text/json": {
                "schema": {
                  "$ref": "#/components/schemas/Address"
                }
              }
            }
          }
        }
      },
      "put": {
        "tags": [
          "Address"
        ],
        "parameters": [
          {
            "name": "id",
            "in": "path",
            "required": true,
            "schema": {
              "type": "integer",
              "format": "int32"
            }
          }
        ],
        "requestBody": {
          "content": {
            "application/json": {
              "schema": {
                "$ref": "#/components/schemas/Address"
              }
            },
            "text/json": {
              "schema": {
                "$ref": "#/components/schemas/Address"
              }
            },
            "application/*+json": {
              "schema": {
                "$ref": "#/components/schemas/Address"
              }
            }
          }
        },
        "responses": {
          "200": {
            "description": "OK"
          }
        }
      },
      "delete": {
        "tags": [
          "Address"
        ],
        "parameters": [
          {
            "name": "id",
            "in": "path",
            "required": true,
            "schema": {
              "type": "integer",
              "format": "int32"
            }
          }
        ],
        "responses": {
          "200": {
            "description": "OK"
          }
        }
      }
    },
    "/api/Auth/login": {
      "post": {
        "tags": [
          "Auth"
        ],
        "requestBody": {
          "content": {
            "application/json": {
              "schema": {
                "$ref": "#/components/schemas/LoginRequest"
              }
            },
            "text/json": {
              "schema": {
                "$ref": "#/components/schemas/LoginRequest"
              }
            },
            "application/*+json": {
              "schema": {
                "$ref": "#/components/schemas/LoginRequest"
              }
            }
          }
        },
        "responses": {
          "200": {
            "description": "OK"
          }
        }
      }
    },
    "/api/Auth/register": {
      "post": {
        "tags": [
          "Auth"
        ],
        "requestBody": {
          "content": {
            "application/json": {
              "schema": {
                "$ref": "#/components/schemas/RegisterRequest"
              }
            },
            "text/json": {
              "schema": {
                "$ref": "#/components/schemas/RegisterRequest"
              }
            },
            "application/*+json": {
              "schema": {
                "$ref": "#/components/schemas/RegisterRequest"
              }
            }
          }
        },
        "responses": {
          "200": {
            "description": "OK"
          }
        }
      }
    },
    "/api/Category": {
      "get": {
        "tags": [
          "Category"
        ],
        "responses": {
          "200": {
            "description": "OK",
            "content": {
              "text/plain": {
                "schema": {
                  "type": "array",
                  "items": {
                    "$ref": "#/components/schemas/Category"
                  }
                }
              },
              "application/json": {
                "schema": {
                  "type": "array",
                  "items": {
                    "$ref": "#/components/schemas/Category"
                  }
                }
              },
              "text/json": {
                "schema": {
                  "type": "array",
                  "items": {
                    "$ref": "#/components/schemas/Category"
                  }
                }
              }
            }
          }
        }
      },
      "post": {
        "tags": [
          "Category"
        ],
        "requestBody": {
          "content": {
            "application/json": {
              "schema": {
                "$ref": "#/components/schemas/Category"
              }
            },
            "text/json": {
              "schema": {
                "$ref": "#/components/schemas/Category"
              }
            },
            "application/*+json": {
              "schema": {
                "$ref": "#/components/schemas/Category"
              }
            }
          }
        },
        "responses": {
          "200": {
            "description": "OK",
            "content": {
              "text/plain": {
                "schema": {
                  "$ref": "#/components/schemas/Category"
                }
              },
              "application/json": {
                "schema": {
                  "$ref": "#/components/schemas/Category"
                }
              },
              "text/json": {
                "schema": {
                  "$ref": "#/components/schemas/Category"
                }
              }
            }
          }
        }
      }
    },
    "/api/Category/{id}": {
      "get": {
        "tags": [
          "Category"
        ],
        "parameters": [
          {
            "name": "id",
            "in": "path",
            "required": true,
            "schema": {
              "type": "integer",
              "format": "int32"
            }
          }
        ],
        "responses": {
          "200": {
            "description": "OK",
            "content": {
              "text/plain": {
                "schema": {
                  "$ref": "#/components/schemas/Category"
                }
              },
              "application/json": {
                "schema": {
                  "$ref": "#/components/schemas/Category"
                }
              },
              "text/json": {
                "schema": {
                  "$ref": "#/components/schemas/Category"
                }
              }
            }
          }
        }
      },
      "put": {
        "tags": [
          "Category"
        ],
        "parameters": [
          {
            "name": "id",
            "in": "path",
            "required": true,
            "schema": {
              "type": "integer",
              "format": "int32"
            }
          }
        ],
        "requestBody": {
          "content": {
            "application/json": {
              "schema": {
                "$ref": "#/components/schemas/Category"
              }
            },
            "text/json": {
              "schema": {
                "$ref": "#/components/schemas/Category"
              }
            },
            "application/*+json": {
              "schema": {
                "$ref": "#/components/schemas/Category"
              }
            }
          }
        },
        "responses": {
          "200": {
            "description": "OK"
          }
        }
      },
      "delete": {
        "tags": [
          "Category"
        ],
        "parameters": [
          {
            "name": "id",
            "in": "path",
            "required": true,
            "schema": {
              "type": "integer",
              "format": "int32"
            }
          }
        ],
        "responses": {
          "200": {
            "description": "OK"
          }
        }
      }
    },
    "/api/Feedback": {
      "get": {
        "tags": [
          "Feedback"
        ],
        "responses": {
          "200": {
            "description": "OK",
            "content": {
              "text/plain": {
                "schema": {
                  "type": "array",
                  "items": {
                    "$ref": "#/components/schemas/Feedback"
                  }
                }
              },
              "application/json": {
                "schema": {
                  "type": "array",
                  "items": {
                    "$ref": "#/components/schemas/Feedback"
                  }
                }
              },
              "text/json": {
                "schema": {
                  "type": "array",
                  "items": {
                    "$ref": "#/components/schemas/Feedback"
                  }
                }
              }
            }
          }
        }
      },
      "post": {
        "tags": [
          "Feedback"
        ],
        "requestBody": {
          "content": {
            "application/json": {
              "schema": {
                "$ref": "#/components/schemas/Feedback"
              }
            },
            "text/json": {
              "schema": {
                "$ref": "#/components/schemas/Feedback"
              }
            },
            "application/*+json": {
              "schema": {
                "$ref": "#/components/schemas/Feedback"
              }
            }
          }
        },
        "responses": {
          "200": {
            "description": "OK",
            "content": {
              "text/plain": {
                "schema": {
                  "$ref": "#/components/schemas/Feedback"
                }
              },
              "application/json": {
                "schema": {
                  "$ref": "#/components/schemas/Feedback"
                }
              },
              "text/json": {
                "schema": {
                  "$ref": "#/components/schemas/Feedback"
                }
              }
            }
          }
        }
      }
    },
    "/api/Feedback/{id}": {
      "get": {
        "tags": [
          "Feedback"
        ],
        "parameters": [
          {
            "name": "id",
            "in": "path",
            "required": true,
            "schema": {
              "type": "integer",
              "format": "int32"
            }
          }
        ],
        "responses": {
          "200": {
            "description": "OK",
            "content": {
              "text/plain": {
                "schema": {
                  "$ref": "#/components/schemas/Feedback"
                }
              },
              "application/json": {
                "schema": {
                  "$ref": "#/components/schemas/Feedback"
                }
              },
              "text/json": {
                "schema": {
                  "$ref": "#/components/schemas/Feedback"
                }
              }
            }
          }
        }
      },
      "put": {
        "tags": [
          "Feedback"
        ],
        "parameters": [
          {
            "name": "id",
            "in": "path",
            "required": true,
            "schema": {
              "type": "integer",
              "format": "int32"
            }
          }
        ],
        "requestBody": {
          "content": {
            "application/json": {
              "schema": {
                "$ref": "#/components/schemas/Feedback"
              }
            },
            "text/json": {
              "schema": {
                "$ref": "#/components/schemas/Feedback"
              }
            },
            "application/*+json": {
              "schema": {
                "$ref": "#/components/schemas/Feedback"
              }
            }
          }
        },
        "responses": {
          "200": {
            "description": "OK"
          }
        }
      },
      "delete": {
        "tags": [
          "Feedback"
        ],
        "parameters": [
          {
            "name": "id",
            "in": "path",
            "required": true,
            "schema": {
              "type": "integer",
              "format": "int32"
            }
          }
        ],
        "responses": {
          "200": {
            "description": "OK"
          }
        }
      }
    },
    "/api/Order": {
      "get": {
        "tags": [
          "Order"
        ],
        "responses": {
          "200": {
            "description": "OK",
            "content": {
              "text/plain": {
                "schema": {
                  "type": "array",
                  "items": {
                    "$ref": "#/components/schemas/Order"
                  }
                }
              },
              "application/json": {
                "schema": {
                  "type": "array",
                  "items": {
                    "$ref": "#/components/schemas/Order"
                  }
                }
              },
              "text/json": {
                "schema": {
                  "type": "array",
                  "items": {
                    "$ref": "#/components/schemas/Order"
                  }
                }
              }
            }
          }
        }
      },
      "post": {
        "tags": [
          "Order"
        ],
        "requestBody": {
          "content": {
            "application/json": {
              "schema": {
                "$ref": "#/components/schemas/Order"
              }
            },
            "text/json": {
              "schema": {
                "$ref": "#/components/schemas/Order"
              }
            },
            "application/*+json": {
              "schema": {
                "$ref": "#/components/schemas/Order"
              }
            }
          }
        },
        "responses": {
          "200": {
            "description": "OK",
            "content": {
              "text/plain": {
                "schema": {
                  "$ref": "#/components/schemas/Order"
                }
              },
              "application/json": {
                "schema": {
                  "$ref": "#/components/schemas/Order"
                }
              },
              "text/json": {
                "schema": {
                  "$ref": "#/components/schemas/Order"
                }
              }
            }
          }
        }
      }
    },
    "/api/Order/{id}": {
      "get": {
        "tags": [
          "Order"
        ],
        "parameters": [
          {
            "name": "id",
            "in": "path",
            "required": true,
            "schema": {
              "type": "integer",
              "format": "int32"
            }
          }
        ],
        "responses": {
          "200": {
            "description": "OK",
            "content": {
              "text/plain": {
                "schema": {
                  "$ref": "#/components/schemas/Order"
                }
              },
              "application/json": {
                "schema": {
                  "$ref": "#/components/schemas/Order"
                }
              },
              "text/json": {
                "schema": {
                  "$ref": "#/components/schemas/Order"
                }
              }
            }
          }
        }
      },
      "put": {
        "tags": [
          "Order"
        ],
        "parameters": [
          {
            "name": "id",
            "in": "path",
            "required": true,
            "schema": {
              "type": "integer",
              "format": "int32"
            }
          }
        ],
        "requestBody": {
          "content": {
            "application/json": {
              "schema": {
                "$ref": "#/components/schemas/Order"
              }
            },
            "text/json": {
              "schema": {
                "$ref": "#/components/schemas/Order"
              }
            },
            "application/*+json": {
              "schema": {
                "$ref": "#/components/schemas/Order"
              }
            }
          }
        },
        "responses": {
          "200": {
            "description": "OK"
          }
        }
      },
      "delete": {
        "tags": [
          "Order"
        ],
        "parameters": [
          {
            "name": "id",
            "in": "path",
            "required": true,
            "schema": {
              "type": "integer",
              "format": "int32"
            }
          }
        ],
        "responses": {
          "200": {
            "description": "OK"
          }
        }
      }
    },
    "/api/OrderDetail": {
      "get": {
        "tags": [
          "OrderDetail"
        ],
        "responses": {
          "200": {
            "description": "OK",
            "content": {
              "text/plain": {
                "schema": {
                  "type": "array",
                  "items": {
                    "$ref": "#/components/schemas/OrderDetail"
                  }
                }
              },
              "application/json": {
                "schema": {
                  "type": "array",
                  "items": {
                    "$ref": "#/components/schemas/OrderDetail"
                  }
                }
              },
              "text/json": {
                "schema": {
                  "type": "array",
                  "items": {
                    "$ref": "#/components/schemas/OrderDetail"
                  }
                }
              }
            }
          }
        }
      },
      "post": {
        "tags": [
          "OrderDetail"
        ],
        "requestBody": {
          "content": {
            "application/json": {
              "schema": {
                "$ref": "#/components/schemas/OrderDetail"
              }
            },
            "text/json": {
              "schema": {
                "$ref": "#/components/schemas/OrderDetail"
              }
            },
            "application/*+json": {
              "schema": {
                "$ref": "#/components/schemas/OrderDetail"
              }
            }
          }
        },
        "responses": {
          "200": {
            "description": "OK",
            "content": {
              "text/plain": {
                "schema": {
                  "$ref": "#/components/schemas/OrderDetail"
                }
              },
              "application/json": {
                "schema": {
                  "$ref": "#/components/schemas/OrderDetail"
                }
              },
              "text/json": {
                "schema": {
                  "$ref": "#/components/schemas/OrderDetail"
                }
              }
            }
          }
        }
      }
    },
    "/api/OrderDetail/{id}": {
      "get": {
        "tags": [
          "OrderDetail"
        ],
        "parameters": [
          {
            "name": "id",
            "in": "path",
            "required": true,
            "schema": {
              "type": "integer",
              "format": "int32"
            }
          }
        ],
        "responses": {
          "200": {
            "description": "OK",
            "content": {
              "text/plain": {
                "schema": {
                  "$ref": "#/components/schemas/OrderDetail"
                }
              },
              "application/json": {
                "schema": {
                  "$ref": "#/components/schemas/OrderDetail"
                }
              },
              "text/json": {
                "schema": {
                  "$ref": "#/components/schemas/OrderDetail"
                }
              }
            }
          }
        }
      },
      "put": {
        "tags": [
          "OrderDetail"
        ],
        "parameters": [
          {
            "name": "id",
            "in": "path",
            "required": true,
            "schema": {
              "type": "integer",
              "format": "int32"
            }
          }
        ],
        "requestBody": {
          "content": {
            "application/json": {
              "schema": {
                "$ref": "#/components/schemas/OrderDetail"
              }
            },
            "text/json": {
              "schema": {
                "$ref": "#/components/schemas/OrderDetail"
              }
            },
            "application/*+json": {
              "schema": {
                "$ref": "#/components/schemas/OrderDetail"
              }
            }
          }
        },
        "responses": {
          "200": {
            "description": "OK"
          }
        }
      },
      "delete": {
        "tags": [
          "OrderDetail"
        ],
        "parameters": [
          {
            "name": "id",
            "in": "path",
            "required": true,
            "schema": {
              "type": "integer",
              "format": "int32"
            }
          }
        ],
        "responses": {
          "200": {
            "description": "OK"
          }
        }
      }
    },
    "/api/Products": {
      "get": {
        "tags": [
          "Products"
        ],
        "responses": {
          "200": {
            "description": "OK",
            "content": {
              "text/plain": {
                "schema": {
                  "type": "array",
                  "items": {
                    "$ref": "#/components/schemas/Product"
                  }
                }
              },
              "application/json": {
                "schema": {
                  "type": "array",
                  "items": {
                    "$ref": "#/components/schemas/Product"
                  }
                }
              },
              "text/json": {
                "schema": {
                  "type": "array",
                  "items": {
                    "$ref": "#/components/schemas/Product"
                  }
                }
              }
            }
          }
        }
      }
    },
    "/api/Products/{id}": {
      "get": {
        "tags": [
          "Products"
        ],
        "parameters": [
          {
            "name": "id",
            "in": "path",
            "required": true,
            "schema": {
              "type": "integer",
              "format": "int32"
            }
          }
        ],
        "responses": {
          "200": {
            "description": "OK",
            "content": {
              "text/plain": {
                "schema": {
                  "$ref": "#/components/schemas/Product"
                }
              },
              "application/json": {
                "schema": {
                  "$ref": "#/components/schemas/Product"
                }
              },
              "text/json": {
                "schema": {
                  "$ref": "#/components/schemas/Product"
                }
              }
            }
          }
        }
      }
    },
    "/api/Promotions": {
      "get": {
        "tags": [
          "Promotions"
        ],
        "responses": {
          "200": {
            "description": "OK"
          }
        }
      }
    },
    "/api/Promotions/{id}": {
      "get": {
        "tags": [
          "Promotions"
        ],
        "parameters": [
          {
            "name": "id",
            "in": "path",
            "required": true,
            "schema": {
              "type": "integer",
              "format": "int32"
            }
          }
        ],
        "responses": {
          "200": {
            "description": "OK"
          }
        }
      }
    },
    "/api/Rankings": {
      "get": {
        "tags": [
          "Rankings"
        ],
        "parameters": [
          {
            "name": "period",
            "in": "query",
            "schema": {
              "type": "string",
              "default": "Weekly"
            }
          }
        ],
        "responses": {
          "200": {
            "description": "OK"
          }
        }
      }
    },
    "/api/Recommendations/{productId}": {
      "get": {
        "tags": [
          "Recommendations"
        ],
        "parameters": [
          {
            "name": "productId",
            "in": "path",
            "required": true,
            "schema": {
              "type": "integer",
              "format": "int32"
            }
          }
        ],
        "responses": {
          "200": {
            "description": "OK",
            "content": {
              "text/plain": {
                "schema": {
                  "type": "array",
                  "items": {
                    "$ref": "#/components/schemas/Product"
                  }
                }
              },
              "application/json": {
                "schema": {
                  "type": "array",
                  "items": {
                    "$ref": "#/components/schemas/Product"
                  }
                }
              },
              "text/json": {
                "schema": {
                  "type": "array",
                  "items": {
                    "$ref": "#/components/schemas/Product"
                  }
                }
              }
            }
          }
        }
      }
    },
    "/api/SubCategory": {
      "get": {
        "tags": [
          "SubCategory"
        ],
        "responses": {
          "200": {
            "description": "OK",
            "content": {
              "text/plain": {
                "schema": {
                  "type": "array",
                  "items": {
                    "$ref": "#/components/schemas/SubCategory"
                  }
                }
              },
              "application/json": {
                "schema": {
                  "type": "array",
                  "items": {
                    "$ref": "#/components/schemas/SubCategory"
                  }
                }
              },
              "text/json": {
                "schema": {
                  "type": "array",
                  "items": {
                    "$ref": "#/components/schemas/SubCategory"
                  }
                }
              }
            }
          }
        }
      },
      "post": {
        "tags": [
          "SubCategory"
        ],
        "requestBody": {
          "content": {
            "application/json": {
              "schema": {
                "$ref": "#/components/schemas/SubCategory"
              }
            },
            "text/json": {
              "schema": {
                "$ref": "#/components/schemas/SubCategory"
              }
            },
            "application/*+json": {
              "schema": {
                "$ref": "#/components/schemas/SubCategory"
              }
            }
          }
        },
        "responses": {
          "200": {
            "description": "OK",
            "content": {
              "text/plain": {
                "schema": {
                  "$ref": "#/components/schemas/SubCategory"
                }
              },
              "application/json": {
                "schema": {
                  "$ref": "#/components/schemas/SubCategory"
                }
              },
              "text/json": {
                "schema": {
                  "$ref": "#/components/schemas/SubCategory"
                }
              }
            }
          }
        }
      }
    },
    "/api/SubCategory/{id}": {
      "get": {
        "tags": [
          "SubCategory"
        ],
        "parameters": [
          {
            "name": "id",
            "in": "path",
            "required": true,
            "schema": {
              "type": "integer",
              "format": "int32"
            }
          }
        ],
        "responses": {
          "200": {
            "description": "OK",
            "content": {
              "text/plain": {
                "schema": {
                  "$ref": "#/components/schemas/SubCategory"
                }
              },
              "application/json": {
                "schema": {
                  "$ref": "#/components/schemas/SubCategory"
                }
              },
              "text/json": {
                "schema": {
                  "$ref": "#/components/schemas/SubCategory"
                }
              }
            }
          }
        }
      },
      "put": {
        "tags": [
          "SubCategory"
        ],
        "parameters": [
          {
            "name": "id",
            "in": "path",
            "required": true,
            "schema": {
              "type": "integer",
              "format": "int32"
            }
          }
        ],
        "requestBody": {
          "content": {
            "application/json": {
              "schema": {
                "$ref": "#/components/schemas/SubCategory"
              }
            },
            "text/json": {
              "schema": {
                "$ref": "#/components/schemas/SubCategory"
              }
            },
            "application/*+json": {
              "schema": {
                "$ref": "#/components/schemas/SubCategory"
              }
            }
          }
        },
        "responses": {
          "200": {
            "description": "OK"
          }
        }
      },
      "delete": {
        "tags": [
          "SubCategory"
        ],
        "parameters": [
          {
            "name": "id",
            "in": "path",
            "required": true,
            "schema": {
              "type": "integer",
              "format": "int32"
            }
          }
        ],
        "responses": {
          "200": {
            "description": "OK"
          }
        }
      }
    },
    "/api/Suggestion": {
      "get": {
        "tags": [
          "Suggestion"
        ],
        "responses": {
          "200": {
            "description": "OK",
            "content": {
              "text/plain": {
                "schema": {
                  "type": "array",
                  "items": {
                    "$ref": "#/components/schemas/Suggestion"
                  }
                }
              },
              "application/json": {
                "schema": {
                  "type": "array",
                  "items": {
                    "$ref": "#/components/schemas/Suggestion"
                  }
                }
              },
              "text/json": {
                "schema": {
                  "type": "array",
                  "items": {
                    "$ref": "#/components/schemas/Suggestion"
                  }
                }
              }
            }
          }
        }
      },
      "post": {
        "tags": [
          "Suggestion"
        ],
        "requestBody": {
          "content": {
            "application/json": {
              "schema": {
                "$ref": "#/components/schemas/Suggestion"
              }
            },
            "text/json": {
              "schema": {
                "$ref": "#/components/schemas/Suggestion"
              }
            },
            "application/*+json": {
              "schema": {
                "$ref": "#/components/schemas/Suggestion"
              }
            }
          }
        },
        "responses": {
          "200": {
            "description": "OK",
            "content": {
              "text/plain": {
                "schema": {
                  "$ref": "#/components/schemas/Suggestion"
                }
              },
              "application/json": {
                "schema": {
                  "$ref": "#/components/schemas/Suggestion"
                }
              },
              "text/json": {
                "schema": {
                  "$ref": "#/components/schemas/Suggestion"
                }
              }
            }
          }
        }
      }
    },
    "/api/Suggestion/{id}": {
      "get": {
        "tags": [
          "Suggestion"
        ],
        "parameters": [
          {
            "name": "id",
            "in": "path",
            "required": true,
            "schema": {
              "type": "integer",
              "format": "int32"
            }
          }
        ],
        "responses": {
          "200": {
            "description": "OK",
            "content": {
              "text/plain": {
                "schema": {
                  "$ref": "#/components/schemas/Suggestion"
                }
              },
              "application/json": {
                "schema": {
                  "$ref": "#/components/schemas/Suggestion"
                }
              },
              "text/json": {
                "schema": {
                  "$ref": "#/components/schemas/Suggestion"
                }
              }
            }
          }
        }
      },
      "put": {
        "tags": [
          "Suggestion"
        ],
        "parameters": [
          {
            "name": "id",
            "in": "path",
            "required": true,
            "schema": {
              "type": "integer",
              "format": "int32"
            }
          }
        ],
        "requestBody": {
          "content": {
            "application/json": {
              "schema": {
                "$ref": "#/components/schemas/Suggestion"
              }
            },
            "text/json": {
              "schema": {
                "$ref": "#/components/schemas/Suggestion"
              }
            },
            "application/*+json": {
              "schema": {
                "$ref": "#/components/schemas/Suggestion"
              }
            }
          }
        },
        "responses": {
          "200": {
            "description": "OK"
          }
        }
      },
      "delete": {
        "tags": [
          "Suggestion"
        ],
        "parameters": [
          {
            "name": "id",
            "in": "path",
            "required": true,
            "schema": {
              "type": "integer",
              "format": "int32"
            }
          }
        ],
        "responses": {
          "200": {
            "description": "OK"
          }
        }
      }
    },
    "/api/Topping": {
      "get": {
        "tags": [
          "Topping"
        ],
        "responses": {
          "200": {
            "description": "OK",
            "content": {
              "text/plain": {
                "schema": {
                  "type": "array",
                  "items": {
                    "$ref": "#/components/schemas/Topping"
                  }
                }
              },
              "application/json": {
                "schema": {
                  "type": "array",
                  "items": {
                    "$ref": "#/components/schemas/Topping"
                  }
                }
              },
              "text/json": {
                "schema": {
                  "type": "array",
                  "items": {
                    "$ref": "#/components/schemas/Topping"
                  }
                }
              }
            }
          }
        }
      },
      "post": {
        "tags": [
          "Topping"
        ],
        "requestBody": {
          "content": {
            "application/json": {
              "schema": {
                "$ref": "#/components/schemas/Topping"
              }
            },
            "text/json": {
              "schema": {
                "$ref": "#/components/schemas/Topping"
              }
            },
            "application/*+json": {
              "schema": {
                "$ref": "#/components/schemas/Topping"
              }
            }
          }
        },
        "responses": {
          "200": {
            "description": "OK",
            "content": {
              "text/plain": {
                "schema": {
                  "$ref": "#/components/schemas/Topping"
                }
              },
              "application/json": {
                "schema": {
                  "$ref": "#/components/schemas/Topping"
                }
              },
              "text/json": {
                "schema": {
                  "$ref": "#/components/schemas/Topping"
                }
              }
            }
          }
        }
      }
    },
    "/api/Topping/{id}": {
      "get": {
        "tags": [
          "Topping"
        ],
        "parameters": [
          {
            "name": "id",
            "in": "path",
            "required": true,
            "schema": {
              "type": "integer",
              "format": "int32"
            }
          }
        ],
        "responses": {
          "200": {
            "description": "OK",
            "content": {
              "text/plain": {
                "schema": {
                  "$ref": "#/components/schemas/Topping"
                }
              },
              "application/json": {
                "schema": {
                  "$ref": "#/components/schemas/Topping"
                }
              },
              "text/json": {
                "schema": {
                  "$ref": "#/components/schemas/Topping"
                }
              }
            }
          }
        }
      },
      "put": {
        "tags": [
          "Topping"
        ],
        "parameters": [
          {
            "name": "id",
            "in": "path",
            "required": true,
            "schema": {
              "type": "integer",
              "format": "int32"
            }
          }
        ],
        "requestBody": {
          "content": {
            "application/json": {
              "schema": {
                "$ref": "#/components/schemas/Topping"
              }
            },
            "text/json": {
              "schema": {
                "$ref": "#/components/schemas/Topping"
              }
            },
            "application/*+json": {
              "schema": {
                "$ref": "#/components/schemas/Topping"
              }
            }
          }
        },
        "responses": {
          "200": {
            "description": "OK"
          }
        }
      },
      "delete": {
        "tags": [
          "Topping"
        ],
        "parameters": [
          {
            "name": "id",
            "in": "path",
            "required": true,
            "schema": {
              "type": "integer",
              "format": "int32"
            }
          }
        ],
        "responses": {
          "200": {
            "description": "OK"
          }
        }
      }
    },
    "/api/User": {
      "get": {
        "tags": [
          "User"
        ],
        "responses": {
          "200": {
            "description": "OK",
            "content": {
              "text/plain": {
                "schema": {
                  "type": "array",
                  "items": {
                    "$ref": "#/components/schemas/User"
                  }
                }
              },
              "application/json": {
                "schema": {
                  "type": "array",
                  "items": {
                    "$ref": "#/components/schemas/User"
                  }
                }
              },
              "text/json": {
                "schema": {
                  "type": "array",
                  "items": {
                    "$ref": "#/components/schemas/User"
                  }
                }
              }
            }
          }
        }
      },
      "post": {
        "tags": [
          "User"
        ],
        "requestBody": {
          "content": {
            "application/json": {
              "schema": {
                "$ref": "#/components/schemas/User"
              }
            },
            "text/json": {
              "schema": {
                "$ref": "#/components/schemas/User"
              }
            },
            "application/*+json": {
              "schema": {
                "$ref": "#/components/schemas/User"
              }
            }
          }
        },
        "responses": {
          "200": {
            "description": "OK",
            "content": {
              "text/plain": {
                "schema": {
                  "$ref": "#/components/schemas/User"
                }
              },
              "application/json": {
                "schema": {
                  "$ref": "#/components/schemas/User"
                }
              },
              "text/json": {
                "schema": {
                  "$ref": "#/components/schemas/User"
                }
              }
            }
          }
        }
      }
    },
    "/api/User/{id}": {
      "get": {
        "tags": [
          "User"
        ],
        "parameters": [
          {
            "name": "id",
            "in": "path",
            "required": true,
            "schema": {
              "type": "integer",
              "format": "int32"
            }
          }
        ],
        "responses": {
          "200": {
            "description": "OK",
            "content": {
              "text/plain": {
                "schema": {
                  "$ref": "#/components/schemas/User"
                }
              },
              "application/json": {
                "schema": {
                  "$ref": "#/components/schemas/User"
                }
              },
              "text/json": {
                "schema": {
                  "$ref": "#/components/schemas/User"
                }
              }
            }
          }
        }
      },
      "put": {
        "tags": [
          "User"
        ],
        "parameters": [
          {
            "name": "id",
            "in": "path",
            "required": true,
            "schema": {
              "type": "integer",
              "format": "int32"
            }
          }
        ],
        "requestBody": {
          "content": {
            "application/json": {
              "schema": {
                "$ref": "#/components/schemas/User"
              }
            },
            "text/json": {
              "schema": {
                "$ref": "#/components/schemas/User"
              }
            },
            "application/*+json": {
              "schema": {
                "$ref": "#/components/schemas/User"
              }
            }
          }
        },
        "responses": {
          "200": {
            "description": "OK"
          }
        }
      },
      "delete": {
        "tags": [
          "User"
        ],
        "parameters": [
          {
            "name": "id",
            "in": "path",
            "required": true,
            "schema": {
              "type": "integer",
              "format": "int32"
            }
          }
        ],
        "responses": {
          "200": {
            "description": "OK"
          }
        }
      }
    }
  },
  "components": {
    "schemas": {
      "Address": {
        "type": "object",
        "properties": {
          "AddressID": {
            "type": "integer",
            "format": "int32"
          },
          "UserID": {
            "type": "integer",
            "format": "int32"
          },
          "AddressName": {
            "type": "string",
            "nullable": true
          },
          "IsDefault": {
            "type": "boolean"
          },
          "CreatedDate": {
            "type": "string",
            "format": "date-time"
          }
        },
        "additionalProperties": false
      },
      "Category": {
        "type": "object",
        "properties": {
          "CategoryID": {
            "type": "integer",
            "format": "int32"
          },
          "CategoryName": {
            "type": "string",
            "nullable": true
          },
          "CreatedDate": {
            "type": "string",
            "format": "date-time"
          }
        },
        "additionalProperties": false
      },
      "Feedback": {
        "type": "object",
        "properties": {
          "FeedbackID": {
            "type": "integer",
            "format": "int32"
          },
          "ProductID": {
            "type": "integer",
            "format": "int32"
          },
          "OrderID": {
            "type": "integer",
            "format": "int32"
          },
          "UserID": {
            "type": "integer",
            "format": "int32"
          },
          "CrustRating": {
            "type": "integer",
            "format": "int32"
          },
          "SauceRating": {
            "type": "integer",
            "format": "int32"
          },
          "CheeseRating": {
            "type": "integer",
            "format": "int32"
          },
          "ToppingRating": {
            "type": "integer",
            "format": "int32"
          },
          "OverallTasteRating": {
            "type": "integer",
            "format": "int32"
          },
          "PresentationRating": {
            "type": "integer",
            "format": "int32"
          },
          "ServiceRating": {
            "type": "integer",
            "format": "int32"
          },
          "Comment": {
            "type": "string",
            "nullable": true
          },
          "CreatedDate": {
            "type": "string",
            "format": "date-time"
          }
        },
        "additionalProperties": false
      },
      "LoginRequest": {
        "required": [
          "email",
          "password"
        ],
        "type": "object",
        "properties": {
          "email": {
            "type": "string",
            "nullable": true
          },
          "password": {
            "type": "string",
            "nullable": true
          }
        },
        "additionalProperties": false
      },
      "Order": {
        "type": "object",
        "properties": {
          "OrderID": {
            "type": "integer",
            "format": "int32"
          },
          "UserID": {
            "type": "integer",
            "format": "int32"
          },
          "AddressID": {
            "type": "integer",
            "format": "int32",
            "nullable": true
          },
          "OrderDate": {
            "type": "string",
            "format": "date-time"
          },
          "TotalAmount": {
            "type": "number",
            "format": "double"
          },
          "Status": {
            "type": "string",
            "nullable": true
          },
          "PaymentMethod": {
            "type": "string",
            "nullable": true
          },
          "ShippingFee": {
            "type": "number",
            "format": "double"
          },
          "PromotionID": {
            "type": "integer",
            "format": "int32",
            "nullable": true
          },
          "CreatedDate": {
            "type": "string",
            "format": "date-time"
          }
        },
        "additionalProperties": false
      },
      "OrderDetail": {
        "type": "object",
        "properties": {
          "OrderDetailID": {
            "type": "integer",
            "format": "int32"
          },
          "OrderID": {
            "type": "integer",
            "format": "int32"
          },
          "ProductID": {
            "type": "integer",
            "format": "int32"
          },
          "Quantity": {
            "type": "integer",
            "format": "int32"
          },
          "Size": {
            "type": "string",
            "nullable": true
          },
          "CrustType": {
            "type": "string",
            "nullable": true
          },
          "UnitPrice": {
            "type": "number",
            "format": "double"
          },
          "ToppingID": {
            "type": "integer",
            "format": "int32",
            "nullable": true
          },
          "ToppingPrice": {
            "type": "number",
            "format": "double"
          }
        },
        "additionalProperties": false
      },
      "Product": {
        "required": [
          "ProductName"
        ],
        "type": "object",
        "properties": {
          "ProductID": {
            "type": "integer",
            "format": "int32"
          },
          "ProductName": {
            "type": "string",
            "nullable": true
          },
          "Description": {
            "type": "string",
            "nullable": true
          },
          "Price": {
            "type": "number",
            "format": "double"
          },
          "CategoryID": {
            "type": "integer",
            "format": "int32"
          },
          "SubCategoryID": {
            "type": "integer",
            "format": "int32",
            "nullable": true
          },
          "ImageURL": {
            "type": "string",
            "nullable": true
          },
          "CreatedDate": {
            "type": "string",
            "format": "date-time"
          }
        },
        "additionalProperties": false
      },
      "RegisterRequest": {
        "required": [
          "email",
          "passwordHash",
          "phone",
          "username"
        ],
        "type": "object",
        "properties": {
          "username": {
            "minLength": 1,
            "type": "string"
          },
          "email": {
            "minLength": 1,
            "type": "string",
            "format": "email"
          },
          "phone": {
            "minLength": 1,
            "pattern": "^(0|\\+84)(\\d{9})$",
            "type": "string"
          },
          "passwordHash": {
            "minLength": 1,
            "pattern": "^(?=.*[a-z])(?=.*[A-Z])(?=.*\\d).{6,}$",
            "type": "string"
          },
          "profilePicture": {
            "type": "string",
            "nullable": true
          }
        },
        "additionalProperties": false
      },
      "SubCategory": {
        "type": "object",
        "properties": {
          "SubCategoryID": {
            "type": "integer",
            "format": "int32"
          },
          "CategoryID": {
            "type": "integer",
            "format": "int32"
          },
          "SubCategoryName": {
            "type": "string",
            "nullable": true
          },
          "CreatedDate": {
            "type": "string",
            "format": "date-time"
          }
        },
        "additionalProperties": false
      },
      "Suggestion": {
        "type": "object",
        "properties": {
          "SuggestionID": {
            "type": "integer",
            "format": "int32"
          },
          "ProductID": {
            "type": "integer",
            "format": "int32"
          },
          "SuggestedProductID": {
            "type": "integer",
            "format": "int32"
          },
          "Confidence": {
            "type": "number",
            "format": "double"
          },
          "CreatedDate": {
            "type": "string",
            "format": "date-time"
          }
        },
        "additionalProperties": false
      },
      "Topping": {
        "type": "object",
        "properties": {
          "ToppingID": {
            "type": "integer",
            "format": "int32"
          },
          "ToppingName": {
            "type": "string",
            "nullable": true
          },
          "Price": {
            "type": "number",
            "format": "double"
          },
          "ProductID": {
            "type": "integer",
            "format": "int32"
          },
          "CreatedDate": {
            "type": "string",
            "format": "date-time"
          }
        },
        "additionalProperties": false
      },
      "User": {
        "type": "object",
        "properties": {
          "UserID": {
            "type": "integer",
            "format": "int32"
          },
          "UserName": {
            "type": "string",
            "nullable": true
          },
          "Email": {
            "type": "string",
            "nullable": true
          },
          "Phone": {
            "type": "string",
            "nullable": true
          },
          "PasswordHash": {
            "type": "string",
            "nullable": true
          },
          "ProfilePicture": {
            "type": "string",
            "nullable": true
          },
          "CreatedDate": {
            "type": "string",
            "format": "date-time"
          }
        },
        "additionalProperties": false
      }
    }
  }
}